pr_st_cli/__init__.py
pr_st_cli/__main__.py
pr_st_cli/assets/images/ascii_logo.txt
pr_st_cli/commands/new/__init__.py
pr_st_cli/commands/new/cli.py
pr_st_cli/template/keyvault/App.py
pr_st_cli/template/keyvault/vault.py
pr_st_cli/template/multipage/main.py
pr_st_cli/template/multipage/page.py
pr_st_cli/template/pr_st_template/func.py
pr_st_cli/template/streamlit/.gitignore
pr_st_cli/template/streamlit/App.py
pr_st_cli/template/streamlit/README.md
pr_st_cli/template/streamlit/requirements.txt
pr_st_cli/tree.py
pr_st_cli/utils.py
pr_st_cli-0.0.42.dist-info/entry_points.txt
pr_st_cli-0.0.42.dist-info/LICENSE
pr_st_cli-0.0.42.dist-info/WHEEL
pr_st_cli-0.0.42.dist-info/METADATA
pr_st_cli-0.0.42.dist-info/RECORD
