Metadata-Version: 2.1
Name: pr-st-cli
Version: 0.0.42
Summary: pr-st-cli is a CLI package that helps create streamlit templates
Home-page: https://github.com/gamcoh/pr-st-cli
License: MIT
Author: gamcoh
Author-email: cohengamliel8@gmail.com
Requires-Python: >=3.8,<4.0
Classifier: Development Status :: 3 - Alpha
Classifier: Intended Audience :: Developers
Classifier: License :: OSI Approved :: MIT License
Classifier: Operating System :: OS Independent
Classifier: Programming Language :: Python :: 3
Classifier: Programming Language :: Python :: 3.10
Classifier: Programming Language :: Python :: 3.8
Classifier: Programming Language :: Python :: 3.9
Classifier: Topic :: Software Development :: Libraries :: Python Modules
Requires-Dist: azure-identity (>=1.10.0,<2.0.0)
Requires-Dist: azure-keyvault-secrets (>=4.4.0,<5.0.0)
Requires-Dist: click (==8.0.2)
Requires-Dist: isort (>=5.10.1,<6.0.0)
Requires-Dist: rich (>=10.14.0,<11.0.0)
Requires-Dist: typer[all] (>=0.4.0,<0.5.0)
Project-URL: Repository, https://github.com/gamcoh/pr-st-cli
